Metadata-Version: 2.1
Name: invars
Version: 0.1.post2
Summary: Single assignment variables
Home-page: https://github.com/masipcat/invars
Author: Jordi Masip
Author-email: jordi@masip.cat
License: GNU
Platform: UNKNOWN
Provides-Extra: test
